roadxpert/__init__.py
roadxpert/ai.py
roadxpert/config.py
roadxpert/core.py
roadxpert/utils.py
roadxpert-1.0.2.dist-info/licenses/LICENSE
roadxpert-1.0.2.dist-info/METADATA
roadxpert-1.0.2.dist-info/WHEEL
roadxpert-1.0.2.dist-info/top_level.txt
roadxpert-1.0.2.dist-info/RECORD
