Metadata-Version: 2.4
Name: roadxpert
Version: 1.0.2
Summary: AI-powered road safety and condition analysis using RoadXpert AI
Home-page: https://github.com/Arijit-Rakshit
Author: Arijit Rakshit
Author-email: krakshit.1970@gmail.com
License: RoadXpert Restricted Use License
Classifier: Programming Language :: Python :: 3
Classifier: License :: Other/Proprietary License
Classifier: Operating System :: OS Independent
Requires-Python: >=3.8
License-File: LICENSE
Requires-Dist: requests
Dynamic: license-file
